jrvc/__init__.py
jrvc/config.py
jrvc/inference.py
jrvc/myutils.py
jrvc/rmvpe.py
jrvc/vc_infer_pipeline.py
jrvc/configs/32k.json
jrvc/configs/32k_v2.json
jrvc/configs/40k.json
jrvc/configs/48k.json
jrvc/configs/48k_v2.json
jrvc/infer_pack/__init__.py
jrvc/infer_pack/attentions.py
jrvc/infer_pack/commons.py
jrvc/infer_pack/models.py
jrvc/infer_pack/modules.py
jrvc/infer_pack/transforms.py
jrvc/utils/__init__.py
jrvc/utils/downloader.py
jrvc-0.0.1.dev14.dist-info/METADATA
jrvc-0.0.1.dev14.dist-info/WHEEL
jrvc-0.0.1.dev14.dist-info/top_level.txt
jrvc-0.0.1.dev14.dist-info/RECORD
