Metadata-Version: 2.1
Name: jrvc
Version: 0.0.1.dev14
Summary: Libraries for RVC inference
Home-page: UNKNOWN
Author: RVC Community
Author-email: hugo.gonzalezdev@gmail.com
License: MIT
Keywords: RVC,Retrieval,Voice,AI,Conversion
Platform: UNKNOWN
Requires-Python: >=3.8
Requires-Dist: absl-py ==1.4.0
Requires-Dist: aiofiles ==23.1.0
Requires-Dist: aiohttp ==3.8.3
Requires-Dist: aiosignal ==1.3.1
Requires-Dist: altair ==4.2.0
Requires-Dist: antlr4-python3-runtime ==4.8
Requires-Dist: anyio ==3.6.2
Requires-Dist: appdirs ==1.4.4
Requires-Dist: asttokens ==2.2.1
Requires-Dist: async-timeout ==4.0.2
Requires-Dist: attrs ==21.4.0
Requires-Dist: backcall ==0.2.0
Requires-Dist: bitarray ==2.5.1
Requires-Dist: cycler ==0.11.0
Requires-Dist: decorator ==5.1.1
Requires-Dist: edge-tts ==6.1.5
Requires-Dist: elevenlabs ==0.2.21
Requires-Dist: entrypoints ==0.4
Requires-Dist: exceptiongroup ==1.1.3
Requires-Dist: executing ==1.2.0
Requires-Dist: fairseq ==0.12.2
Requires-Dist: faiss-cpu ==1.7.2
Requires-Dist: fastapi ==0.88.0
Requires-Dist: ffmpeg-python ==0.2.0
Requires-Dist: ffmpy ==0.3.1
Requires-Dist: filelock ==3.10.0
Requires-Dist: flatbuffers ==23.5.9
Requires-Dist: fonttools ==4.38.0
Requires-Dist: frozenlist ==1.3.3
Requires-Dist: fsspec ==2022.11.0
Requires-Dist: future ==0.18.2
Requires-Dist: grpcio ==1.51.3
Requires-Dist: h11 ==0.12.0
Requires-Dist: httpcore ==0.15.0
Requires-Dist: httpx ==0.23.0
Requires-Dist: humanfriendly ==10.0
Requires-Dist: hydra-core ==1.0.7
Requires-Dist: idna ==3.4
Requires-Dist: importlib-metadata ==6.0.0
Requires-Dist: importlib-resources ==6.0.0
Requires-Dist: ipython
Requires-Dist: jedi ==0.18.2
Requires-Dist: Jinja2 ==3.1.2
Requires-Dist: joblib ==1.2.0
Requires-Dist: json5 ==0.9.14
Requires-Dist: jsonschema ==4.17.3
Requires-Dist: kiwisolver ==1.4.4
Requires-Dist: librosa ==0.9.1
Requires-Dist: linkify-it-py ==1.0.3
Requires-Dist: llvmlite ==0.39.1
Requires-Dist: lxml ==4.9.3
Requires-Dist: Markdown ==3.4.3
Requires-Dist: matplotlib ==3.6.2
Requires-Dist: matplotlib-inline ==0.1.6
Requires-Dist: mdit-py-plugins ==0.3.3
Requires-Dist: mdurl ==0.1.1
Requires-Dist: mega.py ==1.0.8
Requires-Dist: mpmath ==1.2.1
Requires-Dist: multidict ==6.0.3
Requires-Dist: networkx ==2.8.8
Requires-Dist: noisereduce ==2.0.1
Requires-Dist: numba ==0.56.4
Requires-Dist: numpy ==1.23.5
Requires-Dist: oauthlib ==3.2.2
Requires-Dist: omegaconf ==2.0.6
Requires-Dist: onnx ==1.14.0
Requires-Dist: onnxconverter-common ==1.13.0
Requires-Dist: onnxruntime-gpu ==1.14.1
Requires-Dist: orjson ==3.8.3
Requires-Dist: packaging ==22.0
Requires-Dist: pandas ==1.5.2
Requires-Dist: parso ==0.8.3
Requires-Dist: pathlib ==1.0.1
Requires-Dist: pickleshare ==0.7.5
Requires-Dist: Pillow ==9.3.0
Requires-Dist: pooch ==1.6.0
Requires-Dist: portalocker ==2.6.0
Requires-Dist: praat-parselmouth ==0.4.2
Requires-Dist: praatio ==6.0.1
Requires-Dist: prompt-toolkit ==3.0.39
Requires-Dist: protobuf ==4.22.3
Requires-Dist: pure-eval ==0.2.2
Requires-Dist: pyasn1 ==0.4.8
Requires-Dist: pyasn1-modules ==0.2.8
Requires-Dist: pycparser ==2.21
Requires-Dist: pycryptodome ==3.16.0
Requires-Dist: pydantic ==1.10.2
Requires-Dist: pydub ==0.25.1
Requires-Dist: Pygments ==2.15.1
Requires-Dist: pyparsing ==3.0.9
Requires-Dist: python-dateutil ==2.8.2
Requires-Dist: python-dotenv ==1.0.0
Requires-Dist: python-multipart ==0.0.5
Requires-Dist: pytz ==2022.6
Requires-Dist: pyworld
Requires-Dist: PyYAML ==6.0
Requires-Dist: regex ==2022.10.31
Requires-Dist: requests ==2.28.1
Requires-Dist: requests-oauthlib ==1.3.1
Requires-Dist: resampy ==0.4.2
Requires-Dist: rfc3986 ==1.5.0
Requires-Dist: rich ==13.3.5
Requires-Dist: rsa ==4.9
Requires-Dist: sacrebleu ==2.3.1
Requires-Dist: scikit-learn ==1.2.0
Requires-Dist: scipy ==1.9.3
Requires-Dist: semantic-version ==2.10.0
Requires-Dist: six ==1.16.0
Requires-Dist: skl2onnx ==1.14.1
Requires-Dist: sniffio ==1.3.0
Requires-Dist: sounddevice ==0.4.6
Requires-Dist: soundfile ==0.11.0
Requires-Dist: soupsieve ==2.4.1
Requires-Dist: stack-data ==0.6.2
Requires-Dist: starlette ==0.22.0
Requires-Dist: sympy ==1.11.1
Requires-Dist: tabulate ==0.9.0
Requires-Dist: tenacity ==5.1.5
Requires-Dist: threadpoolctl ==3.1.0
Requires-Dist: toolz ==0.12.0
Requires-Dist: torch ==2.0.0
Requires-Dist: torchcrepe ==0.0.19
Requires-Dist: urllib3 ==1.26.13
Requires-Dist: wget ==3.2
Requires-Dist: yarl ==1.8.2
Requires-Dist: zipp ==3.15.0
Requires-Dist: gdown
